{"legendaryquest_standalone_edit":{"en":"Standalone edit","es":"edición independiente","hi":"स्टैंडअलोन संपादित करें","ar":"تحرير مستقل","pt":"editar standalone","bn":"স্বতন্ত্র সম্পাদনা","ru":"Standalone редактировать","ja":"スタンドアロン編集","pa":"ਇੱਕਲਾ ਸੰਪਾਦਨ","de":"Standalone bearbeiten","jw":"dewekan sunting","zh-cn":"独立编辑","zh-tw":"獨立編輯","id":"standalone mengedit","te":"స్వతంత్ర మార్చు","vi":"chỉnh sửa độc lập","ko":"독립 편집","fr":"modifier autonome","mr":"स्वतंत्र संपादन","ta":"தனித்தியங்கும் தொகு"},"legendaryquest_standalone_action":{"en":"Standalone action","es":"acción independiente","hi":"स्टैंडअलोन कार्रवाई","ar":"عمل مستقل","pt":"ação standalone","bn":"স্বতন্ত্র কর্ম","ru":"Автономное действие","ja":"スタンドアロンアクション","pa":"ਇੱਕਲਾ ਕਾਰਵਾਈ ਦੀ","de":"Standalone-Aktion","jw":"tumindak dewekan","zh-cn":"独立行动","zh-tw":"獨立行動","id":"tindakan mandiri","te":"స్వతంత్ర చర్య","vi":"hành động độc lập","ko":"독립형 동작","fr":"une action autonome","mr":"स्वतंत्र कारवाई","ta":"தனித்தியங்கும் நடவடிக்கை"},"legendaryquest_standalone_mission":{"en":"Standalone mission","es":"La misión independiente","hi":"स्टैंडअलोन मिशन","ar":"بعثة مستقلة","pt":"missão standalone","bn":"স্বতন্ত্র মিশন","ru":"Standalone миссия","ja":"スタンドアロンのミッション","pa":"ਇੱਕਲਾ ਮਿਸ਼ਨ","de":"Standalone-Mission","jw":"misi dewekan","zh-cn":"独立任务","zh-tw":"獨立任務","id":"misi mandiri","te":"స్వతంత్ర మిషన్","vi":"nhiệm vụ độc lập","ko":"독립 임무","fr":"mission autonome","mr":"स्वतंत्र मिशन","ta":"தனித்தியங்கும் பணி"}}